rid.py
regressive_imagery_dictionary-0.2.0.dist-info/LICENSE
regressive_imagery_dictionary-0.2.0.dist-info/METADATA
regressive_imagery_dictionary-0.2.0.dist-info/WHEEL
regressive_imagery_dictionary-0.2.0.dist-info/entry_points.txt
regressive_imagery_dictionary-0.2.0.dist-info/top_level.txt
regressive_imagery_dictionary-0.2.0.dist-info/RECORD
