Metadata-Version: 2.1
Name: regressive-imagery-dictionary
Version: 0.2.0
Summary: The Regressive Imagery Dictionary (RID) is a coding scheme for text analysis that is designed to measure "primordial" and conceptual content.
Home-page: https://github.com/jefftriplett/rid.py
Maintainer: Jeff Triplett
Maintainer-email: jeff.triplett@gmail.com
License: MIT
Platform: UNKNOWN
Classifier: Development Status :: 5 - Production/Stable
Classifier: Environment :: Web Environment
Classifier: Intended Audience :: Developers
Classifier: License :: Public Domain
Classifier: Operating System :: OS Independent
Classifier: Programming Language :: Python
Classifier: Topic :: Utilities
